earthnet_minicuber/__init__.py
earthnet_minicuber/minicuber.py
earthnet_minicuber/plot.py
earthnet_minicuber/provider/__init__.py
earthnet_minicuber/provider/alos.py
earthnet_minicuber/provider/cop30.py
earthnet_minicuber/provider/era5.py
earthnet_minicuber/provider/era5_esdl.py
earthnet_minicuber/provider/esawc.py
earthnet_minicuber/provider/geomorphons.py
earthnet_minicuber/provider/landsat.py
earthnet_minicuber/provider/nasadem.py
earthnet_minicuber/provider/ndviclim.py
earthnet_minicuber/provider/provider_base.py
earthnet_minicuber/provider/sentinel1.py
earthnet_minicuber/provider/soilgrids.py
earthnet_minicuber/provider/srtm.py
earthnet_minicuber/provider/s2/__init__.py
earthnet_minicuber/provider/s2/cloudmask.py
earthnet_minicuber/provider/s2/nbar.py
earthnet_minicuber/provider/s2/sen2flux.py
earthnet_minicuber/provider/s2/sentinel2.py
earthnet_minicuber/provider/s2/utils.py
earthnet_minicuber-0.1.3.dist-info/LICENSE
earthnet_minicuber-0.1.3.dist-info/METADATA
earthnet_minicuber-0.1.3.dist-info/WHEEL
earthnet_minicuber-0.1.3.dist-info/top_level.txt
earthnet_minicuber-0.1.3.dist-info/RECORD
