Metadata-Version: 2.1
Name: earthnet-minicuber
Version: 0.1.3
Summary: EarthNet Minicuber
Home-page: https://earthnet.tech
Author: Vitus Benson, Christian Requena-Mesa
Author-email: vbenson@bgc-jena.mpg.de
Classifier: Intended Audience :: Science/Research
Classifier: License :: OSI Approved :: MIT License
Classifier: Programming Language :: Python :: 3
License-File: LICENSE
Requires-Dist: torch
Requires-Dist: segmentation-models-pytorch
Requires-Dist: numpy
Requires-Dist: matplotlib
Requires-Dist: pillow
Requires-Dist: xarray
Requires-Dist: zarr
Requires-Dist: dask
Requires-Dist: netcdf4
Requires-Dist: pandas
Requires-Dist: planetary-computer
Requires-Dist: pyproj
Requires-Dist: pystac-client
Requires-Dist: rasterio
Requires-Dist: requests
Requires-Dist: stackstac
Requires-Dist: rioxarray
Requires-Dist: shapely
Requires-Dist: fsspec
Requires-Dist: aiohttp
Requires-Dist: odc-algo
Provides-Extra: ee
Requires-Dist: earthengine-api ; extra == 'ee'
Requires-Dist: wxee ; extra == 'ee'
Requires-Dist: eemont ; extra == 'ee'
